MANIFEST.in
README.rst
setup.py
pycriteo/__init__.py
pycriteo/client.py
pycriteo.egg-info/PKG-INFO
pycriteo.egg-info/SOURCES.txt
pycriteo.egg-info/dependency_links.txt
pycriteo.egg-info/requires.txt
pycriteo.egg-info/top_level.txt