Metadata-Version: 1.0
Name: pycriteo
Version: 0.0.1
Summary: Simple library to access the Criteo API
Home-page: http://github.com/storborg/funniest
Author: Francesco Della Vedova
Author-email: fdellavedova@gmail.com
License: Apache 2.0
Platform: UNKNOWN
